LICENSE
MANIFEST.in
README.md
setup.cfg
setup.py
loggingmixin/__init__.py
python_logging_mixin.egg-info/PKG-INFO
python_logging_mixin.egg-info/SOURCES.txt
python_logging_mixin.egg-info/dependency_links.txt
python_logging_mixin.egg-info/top_level.txt
tests/__init__.py
tests/tests.py