Metadata-Version: 1.1
Name: python-logging-mixin
Version: 0.1.3
Summary: Logging tools as Mixin
Home-page: https://github.com/romaryd/python-logging-mixin
Author: Romary Dupuis
Author-email: romary@me.com
License: The MIT License (MIT)
